lrf/__init__.py
lrf/_base_lrf.py
lrf/_bfgs.py
lrf/_criterion.py
lrf/_linear_models.py
lrf/_node.py
lrf/_preprocessor.py
lrf/lrf.py
linearrf-1.0.2.dist-info/LICENSE.md
linearrf-1.0.2.dist-info/METADATA
linearrf-1.0.2.dist-info/WHEEL
linearrf-1.0.2.dist-info/top_level.txt
linearrf-1.0.2.dist-info/RECORD
